README.txt
setup.py
src/zc/__init__.py
src/zc.recipe.zope3instance.egg-info/PKG-INFO
src/zc.recipe.zope3instance.egg-info/SOURCES.txt
src/zc.recipe.zope3instance.egg-info/dependency_links.txt
src/zc.recipe.zope3instance.egg-info/entry_points.txt
src/zc.recipe.zope3instance.egg-info/namespace_packages.txt
src/zc.recipe.zope3instance.egg-info/requires.txt
src/zc.recipe.zope3instance.egg-info/top_level.txt
src/zc/recipe/__init__.py
src/zc/recipe/zope3instance/__init__.py
