Metadata-Version: 1.0
Name: zc.recipe.zope3instance
Version: 1.0.0a1
Summary: ZC Buildout recipe for defining a Zope 3 instance
Home-page: http://svn.zope.org/zc.recipe.zope3instance
Author: Jim Fulton
Author-email: jim@zope.com
License: ZPL 2.1
Keywords: zope3 buildout
Platform: UNKNOWN
